async_chatgpt_api-1.1.0.dist-info/licenses/LICENSE
chatgpt/__init__.py
chatgpt/_metadata.py
chatgpt/enums.py
chatgpt/errors.py
chatgpt/exceptions.py
chatgpt/py.typed
chatgpt/types.py
chatgpt/gpt_models/__init__.py
chatgpt/gpt_models/_base.py
chatgpt/gpt_models/gpt_35_turbo.py
chatgpt/gpt_models/gpt_4o_mini.py
chatgpt/gpt_models/model_protocol.py
chatgpt/gpt_models/text_generation.py
async_chatgpt_api-1.1.0.dist-info/METADATA
async_chatgpt_api-1.1.0.dist-info/WHEEL
async_chatgpt_api-1.1.0.dist-info/top_level.txt
async_chatgpt_api-1.1.0.dist-info/RECORD
