Metadata-Version: 2.4
Name: async-chatgpt-api
Version: 1.1.0
Summary: Async OpenAI API wrapper - [Incomplete]
Author-email: Rune Tech <runetech2024@gmail.com>
License: The MIT License (MIT)
Project-URL: Homepage, https://github.com/runetech0/async-chatgpt-api
Project-URL: github, https://github.com/runetech0/async-chatgpt-api
Keywords: chatgpt,api,async
Requires-Python: >=3.11
License-File: LICENSE
Requires-Dist: aiohttp>=3.10.10
Requires-Dist: aiohttp_socks==0.9.0
Dynamic: license-file
